dparse2/__init__.py
dparse2/dependencies.py
dparse2/parser.py
dparse2-0.6.1.dist-info/CHANGELOG.rst
dparse2-0.6.1.dist-info/CONTRIBUTING.rst
dparse2-0.6.1.dist-info/LICENSE
dparse2-0.6.1.dist-info/METADATA
dparse2-0.6.1.dist-info/README.rst
dparse2-0.6.1.dist-info/WHEEL
dparse2-0.6.1.dist-info/top_level.txt
dparse2-0.6.1.dist-info/RECORD
