Metadata-Version: 2.1
Name: dparse2
Version: 0.6.1
Summary: A parser for Python dependency files
Home-page: https://github.com/nexB/dparse2
Author: originally from Jannis Gebauer, maintained by AboutCode.org
Author-email: info@nexb.com
License: MIT
Keywords: dparse pypi dependencies tox conda pipfile setup.cfg
Platform: UNKNOWN
Classifier: Development Status :: 5 - Production/Stable
Classifier: Intended Audience :: Developers
Classifier: License :: OSI Approved :: MIT License
Classifier: Natural Language :: English
Classifier: Programming Language :: Python :: 3
Classifier: Programming Language :: Python :: 3.6
Classifier: Programming Language :: Python :: 3.7
Classifier: Programming Language :: Python :: 3.8
Classifier: Programming Language :: Python :: 3.9
Classifier: Programming Language :: Python :: 3.10
Requires-Python: >=3.6
Provides-Extra: pipenv
License-File: LICENSE
License-File: README.rst
License-File: CHANGELOG.rst
License-File: CONTRIBUTING.rst
